bilibili.py
bilibili_sse.py
bilibili_mcp_tools-0.1.1.dist-info/METADATA
bilibili_mcp_tools-0.1.1.dist-info/WHEEL
bilibili_mcp_tools-0.1.1.dist-info/entry_points.txt
bilibili_mcp_tools-0.1.1.dist-info/licenses/LICENSE
bilibili_mcp_tools-0.1.1.dist-info/RECORD
