Metadata-Version: 2.4
Name: bilibili-mcp-tools
Version: 0.1.1
Summary: 哔哩哔哩 MCP 服务器 - 支持搜索、弹幕、用户信息等功能的模型上下文协议服务器
Project-URL: Homepage, https://github.com/bilibili-mcp/bilibili-mcp-server
Project-URL: Repository, https://github.com/bilibili-mcp/bilibili-mcp-server
Project-URL: Documentation, https://github.com/bilibili-mcp/bilibili-mcp-server/blob/main/README.md
Project-URL: Bug Reports, https://github.com/bilibili-mcp/bilibili-mcp-server/issues
Author-email: bilibili-mcp-tools <mcp@example.com>
License: MIT
License-File: LICENSE
Keywords: api,bilibili,b站,danmaku,mcp,search,弹幕
Classifier: Development Status :: 4 - Beta
Classifier: Intended Audience :: Developers
Classifier: License :: OSI Approved :: MIT License
Classifier: Programming Language :: Python :: 3
Classifier: Programming Language :: Python :: 3.9
Classifier: Programming Language :: Python :: 3.10
Classifier: Programming Language :: Python :: 3.11
Classifier: Programming Language :: Python :: 3.12
Classifier: Topic :: Internet :: WWW/HTTP :: Dynamic Content
Classifier: Topic :: Multimedia :: Video
Classifier: Topic :: Software Development :: Libraries :: Python Modules
Requires-Python: >=3.9
Requires-Dist: bilibili-api-python>=17.1.4
Requires-Dist: httpx>=0.28.1
Requires-Dist: mcp[cli]>=1.4.1
Requires-Dist: requests>=2.32.3
